draper_adder/__init__.py
draper_adder/draper_adder.py
draper_adder/main.py
draperrry-0.0.1.dist-info/LICENSE
draperrry-0.0.1.dist-info/METADATA
draperrry-0.0.1.dist-info/WHEEL
draperrry-0.0.1.dist-info/top_level.txt
draperrry-0.0.1.dist-info/RECORD
