Metadata-Version: 2.1
Name: draperrry
Version: 0.0.1
Summary: A small package to add two numbers together within quantum computing
Home-page: https://github.com/rryoung98/QOSF
Author: Ricky Young
Author-email: rickyyoung@qbraid.com
License: UNKNOWN
Platform: UNKNOWN
Classifier: Programming Language :: Python :: 3
Classifier: License :: OSI Approved :: MIT License
Classifier: Operating System :: OS Independent
Requires-Python: >=3.8
License-File: LICENSE
